lang_support/__init__.py
lang_support/lang_support.py
lang_support-1.3.0.dist-info/METADATA
lang_support-1.3.0.dist-info/WHEEL
lang_support-1.3.0.dist-info/licenses/LICENSE
lang_support-1.3.0.dist-info/RECORD
