Metadata-Version: 2.1
Name: lang_support
Version: 1.3.0
Summary: Package that provides an easy API for adding different, easily changeable languages.
Project-URL: Homepage, https://github.com/MateuszFerenc/my_pythons/tree/main/lang_support
Project-URL: Bug Tracker, https://github.com/mateuszferenc/my_pythons/issues
Author-email: Mateusz Ferenc <ferenc.mateusz.priv@gmail.com>
Maintainer-email: Mateusz Ferenc <ferenc.mateusz.priv@gmail.com>
License: MIT License
License-File: LICENSE
Keywords: language,language change,languages,multilangual
Classifier: License :: OSI Approved :: MIT License
Classifier: Operating System :: OS Independent
Classifier: Programming Language :: Python :: 3
Requires-Python: >=3.8
Requires-Dist: simpldlogger>=1.3.0
